config.py
docker_scanner.py
docksec.py
main.py
setup_external_tools.py
utils.py
docksec-2026.1.24.dist-info/licenses/LICENSE
docksec-2026.1.24.dist-info/METADATA
docksec-2026.1.24.dist-info/WHEEL
docksec-2026.1.24.dist-info/entry_points.txt
docksec-2026.1.24.dist-info/top_level.txt
docksec-2026.1.24.dist-info/RECORD
