Metadata-Version: 2.4
Name: docksec
Version: 2026.1.24
Summary: AI-Powered Docker Security Analyzer
Home-page: https://github.com/advaitpatel/DockSec
Author: Advait Patel
Project-URL: Bug Tracker, https://github.com/advaitpatel/DockSec/issues
Project-URL: Documentation, https://github.com/advaitpatel/DockSec/blob/main/README.md
Project-URL: Source Code, https://github.com/advaitpatel/DockSec
Classifier: Programming Language :: Python :: 3
Classifier: License :: OSI Approved :: MIT License
Classifier: Operating System :: OS Independent
Requires-Python: >=3.12
License-File: LICENSE
Requires-Dist: pydantic<3.0.0,>=2.0.0
Requires-Dist: langchain-core<2.0.0,>=0.3.0
Requires-Dist: langchain<2.0.0,>=0.3.0
Requires-Dist: langchain-openai<1.0.0,>=0.2.0
Requires-Dist: python-dotenv<2.0.0,>=1.0.0
Requires-Dist: pandas<3.0.0,>=2.0.0
Requires-Dist: tqdm<5.0.0,>=4.65.0
Requires-Dist: colorama<1.0.0,>=0.4.6
Requires-Dist: rich<14.0.0,>=13.0.0
Requires-Dist: fpdf2<3.0.0,>=2.7.0
Requires-Dist: tenacity<9.0.0,>=8.0.0
Requires-Dist: setuptools>=65.0.0
Dynamic: author
Dynamic: classifier
Dynamic: description
Dynamic: description-content-type
Dynamic: home-page
Dynamic: license-file
Dynamic: project-url
Dynamic: requires-dist
Dynamic: requires-python
Dynamic: summary
